sysaudit-0.3.0.dist-info/LICENSE
sysaudit-0.3.0.dist-info/METADATA
sysaudit-0.3.0.dist-info/WHEEL
sysaudit-0.3.0.dist-info/RECORD
sysaudit/__init__.pyi
sysaudit/_csysaudit.so
sysaudit/py.typed
sysaudit/_csysaudit.pyi
sysaudit/_csysaudit.c
sysaudit/__init__.py
sysaudit/_csysaudit.pyx
