Metadata-Version: 2.1
Name: sysaudit
Version: 0.3.0
Summary: Backport module for sys.audit and sys.addaudithook from Python 3.8
Home-page: https://sysaudit.readthedocs.io/
License: MIT
Author: brettlangdon
Author-email: me@brett.is
Requires-Python: >=2.7, !=3.0.*, !=3.1.*, !=3.2.*, !=3.3.*, !=3.4.*
Classifier: License :: OSI Approved :: MIT License
Classifier: Programming Language :: Python :: 2
Classifier: Programming Language :: Python :: 2.7
Classifier: Programming Language :: Python :: 3
Classifier: Programming Language :: Python :: 3.5
Classifier: Programming Language :: Python :: 3.6
Classifier: Programming Language :: Python :: 3.7
Classifier: Programming Language :: Python :: 3.8
Classifier: Programming Language :: Python :: 3.9
Project-URL: Repository, https://github.com/brettlangdon/sysaudit
